VLSI/Assignment 3/q3/part(c)/ControlUnit.v
module ControlUnit(
    input K1 , K2 , clk , reset,
    output reg subract = 0 ,
    output reg swap = 0 , 
    output reg selectxy = 0 , 
    output loadxr = 0 , 
    output loadyr = 0,
    output reg [1:0] present = 2'b00 , 
    output reg [1:0] next = 2'b00
);

    parameter S0 = 2'b00,
              S1 = 2'b01,
              S2 = 2'b10,
              S3 = 2'b11;
    
    always @(posedge clk) begin
        if(reset == 1) begin
            present <= S0;
        end
        else
            present <= next;
    end

    always @(present , K1 , K2) begin
        next = S0; //default state
        case(present)
            S0 : begin
                if(K1 == 0)
                    next = S3;
                else if((K1 == 1) & (K2 == 1))
                    next = S2;
                else
                    next = S1;
            end
            S1 : begin
                next = S2;
            end
            S2 : begin
                if(K1 == 0)
                    next = S3;
                else if((K1 == 1) & (K2 == 1))
                    next = S2;
                else
                    next = S1;
            end
            S3 : begin
                next = S3;
            end    
        endcase
    end
    always @(*) begin
        subract = (present == S2) ? 1 : 0;
        swap = (present == S1) ? 1 : 0;
        selectxy = (present == S0) ? 1 : 0;
        loadxr = ((present == S0) | (present == S1) | (present == S2)) ? 1 : 0;
        loadyr = ((present == S0) | (present == S1)) ? 1 : 0;
    end

endmodule

VLSI/Assignment 3/q3/part(c)/ControlUnit_tb.v
`include "ControlUnit.v"

module test ();
    reg K1 , K2 , clk , reset; //K1 = (XR > 0) , K2 = (XR >= YR)
    wire reg subract , swap , selectxy , loadxr , loadyr;
    wire reg [1:0] present , next;
    initial clk = 0;
    always #2 clk = ~clk;
    ControlUnit C1(K1 , K2 , clk , reset , 
                  subract , swap ,selectxy , loadxr , loadyr,present , next);
    
    initial begin
        $dumpfile("test.vcd");
        $dumpvars(0 , test);
        
    end
    initial begin
        reset = 0;
        K1 = 0;K2 = 0;
        #40 $finish;
    end
    always #1 K1 = ~K1;
    always #2 K2 = ~K2;
       
endmodule

VLSI/Assignment 3/q3/part(c)/test.vcd
$date
	Fri Apr  2 11:42:13 2021
$end
$version
	Icarus Verilog
$end
$timescale
	1s
$end
$scope module test $end
$var wire 1 ! swap $end
$var wire 1 " subract $end
$var wire 1 # selectxy $end
$var wire 2 $ present [1:0] $end
$var wire 2 % next [1:0] $end
$var wire 1 & loadyr $end
$var wire 1 ' loadxr $end
$var reg 1 ( K1 $end
$var reg 1 ) K2 $end
$var reg 1 * clk $end
$var reg 1 + reset $end
$scope module C1 $end
$var wire 1 ( K1 $end
$var wire 1 ) K2 $end
$var wire 1 * clk $end
$var wire 1 + reset $end
$var reg 1 ' loadxr $end
$var reg 1 & loadyr $end
$var reg 2 , next [1:0] $end
$var reg 2 - present [1:0] $end
$var reg 1 # selectxy $end
$var reg 1 " subract $end
$var reg 1 ! swap $end
$upscope $end
$upscope $end
$enddefinitions $end
#0
$dumpvars
b0 -
b11 ,
0+
0*
0)
0(
1'
1&
b11 %
b0 $
1#
0"
0!
$end
#1
b1 %
b1 ,
1(
#2
0#
1!
b1 $
b1 -
b10 %
b10 ,
0(
1)
1*
#3
b10 %
b10 ,
1(
#4
b10 %
b10 ,
0(
0)
0*
#5
b10 %
b10 ,
1(
#6
0&
0!
1"
b10 $
b10 -
b11 %
b11 ,
0(
1)
1*
#7
b10 %
b10 ,
1(
#8
b11 %
b11 ,
0(
0)
0*
#9
b1 %
b1 ,
1(
#10
1&
1!
0"
b1 $
b1 -
b10 %
b10 ,
0(
1)
1*
#11
b10 %
b10 ,
1(
#12
b10 %
b10 ,
0(
0)
0*
#13
b10 %
b10 ,
1(
#14
0&
0!
1"
b10 $
b10 -
b11 %
b11 ,
0(
1)
1*
#15
b10 %
b10 ,
1(
#16
b11 %
b11 ,
0(
0)
0*
#17
b1 %
b1 ,
1(
#18
1&
1!
0"
b1 $
b1 -
b10 %
b10 ,
0(
1)
1*
#19
b10 %
b10 ,
1(
#20
b10 %
b10 ,
0(
0)
0*
#21
b10 %
b10 ,
1(
#22
0&
0!
1"
b10 $
b10 -
b11 %
b11 ,
0(
1)
1*
#23
b10 %
b10 ,
1(
#24
b11 %
b11 ,
0(
0)
0*
#25
b1 %
b1 ,
1(
#26
1&
1!
0"
b1 $
b1 -
b10 %
b10 ,
0(
1)
1*
#27
b10 %
b10 ,
1(
#28
b10 %
b10 ,
0(
0)
0*
#29
b10 %
b10 ,
1(
#30
0&
0!
1"
b10 $
b10 -
b11 %
b11 ,
0(
1)
1*
#31
b10 %
b10 ,
1(
#32
b11 %
b11 ,
0(
0)
0*
#33
b1 %
b1 ,
1(
#34
1&
1!
0"
b1 $
b1 -
b10 %
b10 ,
0(
1)
1*
#35
b10 %
b10 ,
1(
#36
b10 %
b10 ,
0(
0)
0*
#37
b10 %
b10 ,
1(
#38
0&
0!
1"
b10 $
b10 -
b11 %
b11 ,
0(
1)
1*
#39
b10 %
b10 ,
1(
#40
b11 %
b11 ,
0(
0)
0*
